streamlit_colab/__init__.py
streamlit_colab/core.py
streamlit_colab-0.1.6.dist-info/LICENSE
streamlit_colab-0.1.6.dist-info/METADATA
streamlit_colab-0.1.6.dist-info/WHEEL
streamlit_colab-0.1.6.dist-info/entry_points.txt
streamlit_colab-0.1.6.dist-info/top_level.txt
streamlit_colab-0.1.6.dist-info/RECORD
