Metadata-Version: 2.1
Name: streamlit-colab
Version: 0.1.6
Summary: Run Streamlit apps on Google Colab with ease
Home-page: https://github.com/yourusername/streamlit-colab
Author: Wuhp
Author-email: your.email@example.com
Classifier: Programming Language :: Python :: 3
Classifier: License :: OSI Approved :: MIT License
Classifier: Operating System :: OS Independent
Requires-Python: >=3.6
License-File: LICENSE
Requires-Dist: streamlit>=1.0.0
Requires-Dist: pyngrok>=5.0.0
